audity/__init__.py
audity/__main__.py
audity/audity.py
audity-0.11.0.dist-info/licenses/LICENSE
audity-0.11.0.dist-info/METADATA
audity-0.11.0.dist-info/WHEEL
audity-0.11.0.dist-info/entry_points.txt
audity-0.11.0.dist-info/top_level.txt
audity-0.11.0.dist-info/RECORD
