Metadata-Version: 2.4
Name: audity
Version: 0.11.0
Summary: Audit, inspect, and survey data from the terminal.
Author-email: espehon <espehon@gmail.com>
Project-URL: Homepage, https://github.com/espehon/audity
Project-URL: Bug Tracker, https://github.com/espehon/audity/issues
Classifier: Programming Language :: Python :: 3
Classifier: Development Status :: 3 - Alpha
Classifier: Environment :: Console
Classifier: License :: OSI Approved :: MIT License
Classifier: Operating System :: OS Independent
Classifier: Topic :: Utilities
Classifier: Topic :: Scientific/Engineering :: Information Analysis
Requires-Python: >=3.10
License-File: LICENSE
Requires-Dist: colorama>=0.4.6
Requires-Dist: pandas>=2.3.0
Requires-Dist: numpy<2.0.0,>=1.26.4
Requires-Dist: seaborn>=0.12.2
Requires-Dist: matplotlib>=3.7.1
Requires-Dist: halo>=0.0.31
Requires-Dist: questionary>=2.1.0
Requires-Dist: openpyxl>=3.1.5
Dynamic: license-file
